MANIFEST.in
requirements.txt
setup.py
src/zato/__init__.py
src/zato/apimox/__init__.py
src/zato/apimox/cli.py
src/zato/apimox/common.py
src/zato/apimox/http.py
src/zato/apimox/init.py
src/zato/apimox/run.py
src/zato/apimox/zmq_.py
src/zato/apimox/console/apimox
src/zato_apimox.egg-info/PKG-INFO
src/zato_apimox.egg-info/SOURCES.txt
src/zato_apimox.egg-info/dependency_links.txt
src/zato_apimox.egg-info/namespace_packages.txt
src/zato_apimox.egg-info/not-zip-safe
src/zato_apimox.egg-info/requires.txt
src/zato_apimox.egg-info/top_level.txt