Metadata-Version: 1.1
Name: zato-apimox
Version: 1.3
Summary: Zato API Mox - Human Friendly HTTP and ZeroMQ mocks
Home-page: https://zato.io/docs
Author: Dariusz Suchojad
Author-email: dsuch at zato.io
License: GNU Lesser General Public License v3 (LGPLv3)
Platform: OS Independent
Classifier: Development Status :: 5 - Production/Stable
Classifier: Environment :: Console
Classifier: Environment :: Web Environment
Classifier: Intended Audience :: Developers
Classifier: Intended Audience :: Information Technology
Classifier: Intended Audience :: Other Audience
Classifier: License :: OSI Approved :: GNU Lesser General Public License v3 (LGPLv3)
Classifier: Natural Language :: English
Classifier: Operating System :: OS Independent
Classifier: Programming Language :: Python
Classifier: Programming Language :: Python :: 2
Classifier: Programming Language :: Python :: 3
Classifier: Intended Audience :: Developers
Classifier: Topic :: Communications
Classifier: Topic :: Education :: Testing
Classifier: Topic :: Internet
Classifier: Topic :: Internet :: Proxy Servers
Classifier: Topic :: Internet :: WWW/HTTP
Classifier: Topic :: Security
Classifier: Topic :: Software Development :: Quality Assurance
Classifier: Topic :: Software Development :: Testing
Classifier: Topic :: System :: Networking
Classifier: Topic :: Utilities
